grupob_trace_logger/__init__.py
grupob_trace_logger/log.py
grupob_trace_logger-0.2.0.dist-info/LICENCE
grupob_trace_logger-0.2.0.dist-info/METADATA
grupob_trace_logger-0.2.0.dist-info/WHEEL
grupob_trace_logger-0.2.0.dist-info/top_level.txt
grupob_trace_logger-0.2.0.dist-info/RECORD
